pdfmerger/__init__.py
pdfmerger/main.py
PyPDFMerge-0.0.5.dist-info/LICENSE
PyPDFMerge-0.0.5.dist-info/METADATA
PyPDFMerge-0.0.5.dist-info/WHEEL
PyPDFMerge-0.0.5.dist-info/entry_points.txt
PyPDFMerge-0.0.5.dist-info/top_level.txt
PyPDFMerge-0.0.5.dist-info/RECORD
