Metadata-Version: 2.1
Name: PyPDFMerge
Version: 0.0.5
Summary: Merge individual pages of PDF file into one page
Home-page: https://github.com/shhossain/pdf-merger
Author: sifat (shhossain)
Author-email: <hossain@gmail.com>
Project-URL: Documentation, https://github.com/shhossain/pdf-merger/blob/main/README.md
Project-URL: Source, https://github.com/shhossain/pdf-merger
Project-URL: Bug Report, https://github.com/shhossain/pdf-merger/issues
Keywords: pdf-merger,pdf
Classifier: Development Status :: 3 - Alpha
Classifier: Intended Audience :: Developers
Classifier: Intended Audience :: Education
Classifier: Intended Audience :: Science/Research
Classifier: License :: OSI Approved :: MIT License
Classifier: Programming Language :: Python :: 3.6
Classifier: Programming Language :: Python :: 3.7
Classifier: Programming Language :: Python :: 3.8
Classifier: Programming Language :: Python :: 3.9
Classifier: Programming Language :: Python :: 3.10
Classifier: Topic :: Software Development :: Libraries :: Python Modules
Classifier: Topic :: Utilities
Classifier: Operating System :: OS Independent
Requires-Python: >=3.6
License-File: LICENSE
Requires-Dist: pillow (<=9.5.0)
Requires-Dist: pymupdf (<=1.22.5)
